Workbook
Name AverageTarrifDifferential: 'Values for indicators'!$P$1:$P$5
Name BadDebtProvision: 'Values for indicators'!$AW$1:$AW$5
Name BCEfficiency: 'Values for indicators'!$AZ$1:$AZ$5
Name DebtCashAvailable: 'Values for indicators'!$AN$1:$AN$5
Name DebtorDays: 'Values for indicators'!$AT$1:$AT$5
Name DebtServiceCoverage: 'Values for indicators'!$AH$1:$AH$5
Name DebtToEquity: 'Values for indicators'!$AQ$1:$AQ$5
Name ElectricityCosts: 'Values for indicators'!$V$1:$V$5
Name EmployeeCosts: 'Values for indicators'!$Y$1:$Y$5
Name GrantDependency: 'Values for indicators'!$AK$1:$AK$5
Name MaintenanceCosts: 'Values for indicators'!$S$1:$S$5
Name NonRevenue: 'Values for indicators'!$G$1:$G$5
Name OMCoverage: 'Values for indicators'!$AB$1:$AB$5
Name Percent25_10: 'Values for indicators'!$AE$1:$AE$5
Name PovertyRate: 'Values for indicators'!$A$1:$B$5
Name povertyRateDisplay: 'Values for indicators'!$A$1:$A$5
Name RevenueDiversification: 'Values for indicators'!$M$1:$M$5
Name SanitationCoverage: 'Values for indicators'!$D$1:$D$5
Name StaffConnections: 'Values for indicators'!$J$1:$J$5

Sheet Basis for index score
A1: Question | B1: Options | C1: Value | D1: Weight | E1: Max Value | F1: Definition | G1: Formula | H1: Sources | I1: Links
A2: Poverty Rate | B2: 20-40 | C2: =(VLOOKUP(B2, 'Values for indicators'!A:B, 2, FALSE)*D2) -> 9 | D2: 3 | E2: =(4*D2) -> 12 | F2: Share of population below poverty line | G2: Total number of poor people in the area/ total popullaiton of the area | H2: National statistics office, WB PovCalNet | I2: https://povertydata.worldbank.org
A3: Sanitation Coverage | B3: 90-100 | C3: =(VLOOKUP(B3, 'Values for indicators'!D:E, 2, FALSE)*D3) -> 3 | D3: 1 | E3: =(4*D3) -> 4 | F3: Population with improved/safely managed sanitation | G3: Number of people with access to safe Sanitation Services / Population of the area | H3: Utility sewerage records, FSM operators, JMP | I3: https://washdata.org
A4: Water Coverage | B4: 70-80 | C4: =(VLOOKUP(B4, 'Values for indicators'!D:E, 2, FALSE)*D4) -> 1 | D4: 1 | E4: =(4*D4) -> 4 | F4: Population served with piped/safely managed water | G4: Number of people served with potable Water Supply Services / Population of area | H4: Utility reports, billing registry | I4: https://ib-net.org
A5: Non-Revenue Water | B5: 30-40 | C5: =(VLOOKUP(B5, 'Values for indicators'!G:H, 2, FALSE)*D5) -> 10 | D5: 5 | E5: =(4*D5) -> 20 | F5: Water produced but not billed | G5: Total Volume of Water Lost from Commercial and Physical Losses as a proportion of Water Produced | H5: Production meters, billing system | I5: https://www.iwa-network.org
A6: Staff / 1000 Connection | B6: 7 | C6: =(VLOOKUP(B6, 'Values for indicators'!J:K, 2, FALSE)*D6) -> 6 | D6: 3 | E6: =(4*D6) -> 12 | F6: Number of staff per 1,000 connections | G6: Number of Staff Members / (total number of connections/1000) | H6: HR records, billing connections | I6: https://ib-net.org
A7: Revenue Diversification | B7: >70% | C7: =(VLOOKUP(B7, 'Values for indicators'!M:N, 2, FALSE)*D7) -> 0 | D7: 5 | E7: =(4*D7) -> 20 | F7: Share of non‑tariff revenue | G7: % of residential revenue - % institutional/commercial revenue | H7: Income statement
A8: Average Tariff Differential | B8: 20-35% | C8: =(VLOOKUP(B8, 'Values for indicators'!P:Q, 2, FALSE)*D8) -> 14 | D8: 7 | E8: =(4*D8) -> 28 | F8: Difference between highest & lowest tariff | G8: (100*(Average Tariff - Average Cost)/ Average cost) | H8: Tariff schedule
A9: Maintenance Costs / OPEX | B9: 4-6% | C9: =(VLOOKUP(B9, 'Values for indicators'!S:T, 2, FALSE)*D9) -> 6 | D9: 3 | E9: =(4*D9) -> 12 | F9: Maintenance as % of OPEX | G9: Total Maintenance Costs / total operations and maintenance expenditure | H9: O&M budget, OPEX ledger
A10: Electricity Costs / OPEX | B10: >25% | C10: =(VLOOKUP(B10, 'Values for indicators'!V:W, 2, FALSE)*D10) -> 0 | D10: 2 | E10: =(4*D10) -> 8 | F10: Electricity as % of OPEX | G10: Total Electricity Costs / total operation and maintenance expenditure | H10: Utility energy bills
A11: Employee Costs / OPEX | B11: 35-40% | C11: =(VLOOKUP(B11, 'Values for indicators'!Y:Z, 2, FALSE)*D11) -> 2 | D11: 2 | E11: =(4*D11) -> 8 | F11: Employee costs as % of OPEX | G11: Total Employee Costs (inclusive of salary, pension and other related employee benefits) as % of total OPEX | H11: Income statement
A12: O&M Coverage | B12: 120-130% | C12: =(VLOOKUP(B12, 'Values for indicators'!AB:AC, 2, FALSE)*D12) -> 12 | D12: 4 | E12: =(4*D12) -> 16 | F12: Ability to cover O&M from revenues | G12: Total revenue from water and sewerage sales /total operations and maintenance expenditure | H12: Income statement | I12: https://ib-net.org
A13: EBITDA / Revenue | B13: Less than 10% | C13: =(VLOOKUP(B13, 'Values for indicators'!AE:AF, 2, FALSE)*D13) -> 0 | D13: 5 | E13: =(4*D13) -> 20 | F13: Cash operating margin | G13: Earnings Before Interest Tax, Depreciation and Amortization / Revenue | H13: Financial statements
A14: Cash Reserves | B14: Less than 10% | C14: =(VLOOKUP(B14, 'Values for indicators'!AE:AF, 2, FALSE)*D14) -> 0 | D14: 4 | E14: =(4*D14) -> 16 | F14: Cash on hand relative to OPEX | G14: Cash reserves as % of annual operating income | H14: Balance sheet
A15: Liquidity Ratio | B15: Less than 10% | C15: =(VLOOKUP(B15, 'Values for indicators'!AE:AF, 2, FALSE)*D15) -> 0 | D15: 6 | E15: =(4*D15) -> 24 | F15: Current assets vs liabilities | G15: Cash and near cash reserves / Current Liabilities | H15: Balance sheet
A16: Debt Service Coverage Ratio | B16: >1.8 | C16: =(VLOOKUP(B16, 'Values for indicators'!AH:AI, 2, FALSE)*D16) -> 28 | D16: 7 | E16: =(4*D16) -> 28 | F16: Ability to service debt | G16: Cash flow available for Debt Service / Total Debt Service (Interest + Principa Repayments) | H16: Loan agreements, financial statements
A17: Grant Dependency | B17: 0-10% | C17: =(VLOOKUP(B17, 'Values for indicators'!AK:AL, 2, FALSE)*D17) -> 9 | D17: 3 | E17: =(4*D17) -> 12 | F17: Share of CAPEX financed by grants | G17: Proportion of OPEX financed by income from grants | H17: CAPEX budget
A18: Debt/Cash Available for Debt Service | B18: <0.9 | C18: =(VLOOKUP(B18, 'Values for indicators'!AN:AO, 2, FALSE)*D18) -> 36 | D18: 9 | E18: =(4*D18) -> 36 | F18: Debt vs liquidity for debt | G18: Total debt / Cash available for Debt Service | H18: Balance sheet
A19: Debt to Equity | B19: >35% | C19: =(VLOOKUP(B19, 'Values for indicators'!AQ:AR, 2, FALSE)*D19) -> 0 | D19: 5 | E19: =(4*D19) -> 20 | F19: Leverage ratio | G19: Total Debt / Total Equity | H19: Balance sheet
A20: Debtor Days | B20: >120 days | C20: =(VLOOKUP(B20, 'Values for indicators'!AT:AU, 2, FALSE)*D20) -> 0 | D20: 5 | E20: =(4*D20) -> 20 | F20: Average days to collect bills | G20: Net billed amount outstanding / Total annual operatiing revenues excluding grants and transfers * 365 | H20: Billing system, AR ledger | I20: https://ib-net.org
A21: Reduction in Debtor Days | B21: 20-25% | C21: =(VLOOKUP(B21, 'Values for indicators'!AE:AF, 2, FALSE)*D21) -> 15 | D21: 5 | E21: =(4*D21) -> 20 | F21: Year on Year % reduction | G21: ((Debtor days in current financial year - debtor days in previous year)/ Debtor days in current financial year)) *100 | H21: Billing + AR records
A22: Bad Debt Provision | B22: 60-90 days | C22: =(VLOOKUP(B22, 'Values for indicators'!AW:AX, 2, FALSE)*D22) -> 15 | D22: 5 | E22: =(4*D22) -> 20 | F22: Expected credit losses in days | G22: N of days after an invoice becomes overdue before the utility records a bad debt provision in its accounts | H22: Financial statements
A23: Billing Efficiency | B23: >95% | C23: =(VLOOKUP(B23, 'Values for indicators'!AZ:BA, 2, FALSE)*D23) -> 20 | D23: 5 | E23: =(4*D23) -> 20 | F23: % of consumed water billed | G23: % of Billed water / water produced and/or bought | H23: Billing + meter records | I23: https://ib-net.org
A24: Collection Efficiency | B24: 90-92% | C24: =(VLOOKUP(B24, 'Values for indicators'!AZ:BA, 2, FALSE)*D24) -> 10 | D24: 5 | E24: =(4*D24) -> 20 | F24: % of billed revenue collected | G24: % Cash collected / billed amount | H24: Billing + bank records | I24: https://ib-net.org
A25: Index Final Score (auto-populated from your responses above) | C25: =((SUM(C2:C24) / E25) * 100) -> 49 | D25: =SUM(D2:D24) -> 100 | E25: =SUM(E2:E24) -> 400
A27: Index Final Score before peer reviewers comments applied | C27: 48.5

Sheet Merging O&M
A1: Question | B1: Options | C1: Value | D1: Weight | E1: Max Value | F1: Definition | G1: Formula | H1: Sources | I1: Links
A2: Poverty Rate | B2: 20-40 | C2: =(VLOOKUP(B2, 'Values for indicators'!A:B, 2, FALSE)*D2) -> 9 | D2: 3 | E2: =(4*D2) -> 12 | F2: Share of population below poverty line | G2: Total number of poor people in the area/ total popullaiton of the area | H2: National statistics office, WB PovCalNet | I2: https://povertydata.worldbank.org
A3: Sanitation Coverage | B3: 90-100 | C3: =(VLOOKUP(B3, 'Values for indicators'!D:E, 2, FALSE)*D3) -> 3 | D3: 1 | E3: =(4*D3) -> 4 | F3: Population with improved/safely managed sanitation | G3: Number of people with access to safe Sanitation Services / Population of the area | H3: Utility sewerage records, FSM operators, JMP | I3: https://washdata.org
A4: Water Coverage | B4: 70-80 | C4: =(VLOOKUP(B4, 'Values for indicators'!D:E, 2, FALSE)*D4) -> 1 | D4: 1 | E4: =(4*D4) -> 4 | F4: Population served with piped/safely managed water | G4: Number of people served with potable Water Supply Services / Population of area | H4: Utility reports, billing registry | I4: https://ib-net.org
A5: Non-Revenue Water | B5: 30-40 | C5: =(VLOOKUP(B5, 'Values for indicators'!G:H, 2, FALSE)*D5) -> 10 | D5: 5 | E5: =(4*D5) -> 20 | F5: Water produced but not billed | G5: Total Volume of Water Lost from Commercial and Physical Losses as a proportion of Water Produced | H5: Production meters, billing system | I5: https://www.iwa-network.org
A6: Staff / 1000 Connection | B6: 7 | C6: =(VLOOKUP(B6, 'Values for indicators'!J:K, 2, FALSE)*D6) -> 6 | D6: 3 | E6: =(4*D6) -> 12 | F6: Number of staff per 1,000 connections | G6: Number of Staff Members / (total number of connections/1000) | H6: HR records, billing connections | I6: https://ib-net.org
A7: Revenue Diversification | B7: >70% | C7: =(VLOOKUP(B7, 'Values for indicators'!M:N, 2, FALSE)*D7) -> 0 | D7: 5 | E7: =(4*D7) -> 20 | F7: Share of non‑tariff revenue | G7: % of residential revenue - % institutional/commercial revenue | H7: Income statement
A8: Average Tariff Differential | B8: 20-35% | C8: =(VLOOKUP(B8, 'Values for indicators'!P:Q, 2, FALSE)*D8) -> 14 | D8: 7 | E8: =(4*D8) -> 28 | F8: Difference between highest & lowest tariff | G8: (100*(Average Tariff - Average Cost)/ Average cost) | H8: Tariff schedule
A9: O&M Coverage | B9: 120-130% | C9: =(VLOOKUP(B9, 'Values for indicators'!AB:AC, 2, FALSE)*D9) -> 33 | D9: 11 | E9: =(4*D9) -> 44 | F9: Ability to cover O&M from revenues | G9: Total revenue from water and sewerage sales /total operations and maintenance expenditure | H9: Income statement | I9: https://ib-net.org
A10: EBITDA / Revenue | B10: Less than 10% | C10: =(VLOOKUP(B10, 'Values for indicators'!AE:AF, 2, FALSE)*D10) -> 0 | D10: 5 | E10: =(4*D10) -> 20 | F10: Cash operating margin | G10: Earnings Before Interest Tax, Depreciation and Amortization / Revenue | H10: Financial statements
A11: Cash Reserves | B11: Less than 10% | C11: =(VLOOKUP(B11, 'Values for indicators'!AE:AF, 2, FALSE)*D11) -> 0 | D11: 4 | E11: =(4*D11) -> 16 | F11: Cash on hand relative to OPEX | G11: Cash reserves as % of annual operating income | H11: Balance sheet
A12: Liquidity Ratio | B12: Less than 10% | C12: =(VLOOKUP(B12, 'Values for indicators'!AE:AF, 2, FALSE)*D12) -> 0 | D12: 6 | E12: =(4*D12) -> 24 | F12: Current assets vs liabilities | G12: Cash and near cash reserves / Current Liabilities | H12: Balance sheet
A13: Debt Service Coverage Ratio | B13: >1.8 | C13: =(VLOOKUP(B13, 'Values for indicators'!AH:AI, 2, FALSE)*D13) -> 28 | D13: 7 | E13: =(4*D13) -> 28 | F13: Ability to service debt | G13: Cash flow available for Debt Service / Total Debt Service (Interest + Principa Repayments) | H13: Loan agreements, financial statements
A14: Grant Dependency | B14: 0-10% | C14: =(VLOOKUP(B14, 'Values for indicators'!AK:AL, 2, FALSE)*D14) -> 9 | D14: 3 | E14: =(4*D14) -> 12 | F14: Share of CAPEX financed by grants | G14: Proportion of OPEX financed by income from grants | H14: CAPEX budget
A15: Debt/Cash Available for Debt Service | B15: <0.9 | C15: =(VLOOKUP(B15, 'Values for indicators'!AN:AO, 2, FALSE)*D15) -> 36 | D15: 9 | E15: =(4*D15) -> 36 | F15: Debt vs liquidity for debt | G15: Total debt / Cash available for Debt Service | H15: Balance sheet
A16: Debt to Equity | B16: >35% | C16: =(VLOOKUP(B16, 'Values for indicators'!AQ:AR, 2, FALSE)*D16) -> 0 | D16: 5 | E16: =(4*D16) -> 20 | F16: Leverage ratio | G16: Total Debt / Total Equity | H16: Balance sheet
A17: Debtor Days | B17: >120 days | C17: =(VLOOKUP(B17, 'Values for indicators'!AT:AU, 2, FALSE)*D17) -> 0 | D17: 5 | E17: =(4*D17) -> 20 | F17: Average days to collect bills | G17: Net billed amount outstanding / Total annual operatiing revenues excluding grants and transfers * 365 | H17: Billing system, AR ledger | I17: https://ib-net.org
A18: Reduction in Debtor Days | B18: 20-25% | C18: =(VLOOKUP(B18, 'Values for indicators'!AE:AF, 2, FALSE)*D18) -> 15 | D18: 5 | E18: =(4*D18) -> 20 | F18: Year on Year % reduction | G18: ((Debtor days in current financial year - debtor days in previous year)/ Debtor days in current financial year)) *100 | H18: Billing + AR records
A19: Bad Debt Provision | B19: 60-90 days | C19: =(VLOOKUP(B19, 'Values for indicators'!AW:AX, 2, FALSE)*D19) -> 15 | D19: 5 | E19: =(4*D19) -> 20 | F19: Expected credit losses in days | G19: N of days after an invoice becomes overdue before the utility records a bad debt provision in its accounts | H19: Financial statements
A20: Billing Efficiency | B20: >95% | C20: =(VLOOKUP(B20, 'Values for indicators'!AZ:BA, 2, FALSE)*D20) -> 20 | D20: 5 | E20: =(4*D20) -> 20 | F20: % of consumed water billed | G20: % of Billed water / water produced and/or bought | H20: Billing + meter records | I20: https://ib-net.org
A21: Collection Efficiency | B21: 90-92% | C21: =(VLOOKUP(B21, 'Values for indicators'!AZ:BA, 2, FALSE)*D21) -> 10 | D21: 5 | E21: =(4*D21) -> 20 | F21: % of billed revenue collected | G21: % Cash collected / billed amount | H21: Billing + bank records | I21: https://ib-net.org
A22: Index Final Score (auto-populated from your responses above) | C22: =((SUM(C2:C21) / E22) * 100) -> 52.25 | D22: =SUM(D2:D21) -> 100 | E22: =SUM(E2:E21) -> 400
A24: Index Final Score before peer reviewers comments applied | C24: 48.5

Sheet Values for indicators
A1: 0-20 | B1: 4 | D1: 100 | E1: 4 | G1: <20 | H1: 4 | J1: <5 | K1: 4 | M1: <10% | N1: 4 | P1: >50% | Q1: 4 | S1: >8% | T1: 4 | V1: <10% | W1: 4 | Y1: <25% | Z1: 4 | AB1: >130% | AC1: 4 | AE1: >25% | AF1: 4 | AH1: >1.8 | AI1: 4 | AK1: 0 | AL1: 4 | AN1: <0.9 | AO1: 4 | AQ1: <20% | AR1: 4 | AT1: <45 days | AU1: 4 | AW1: <60 days | AX1: 4 | AZ1: >95% | BA1: 4
A2: 20-40 | B2: 3 | D2: 90-100 | E2: 3 | G2: 20-30 | H2: 3 | J2: 6 | K2: 3 | M2: 10-30% | N2: 3 | P2: 35-50% | Q2: 3 | S2: 6-8% | T2: 3 | V2: 10-15% | W2: 3 | Y2: 25-30% | Z2: 3 | AB2: 120-130% | AC2: 3 | AE2: 20-25% | AF2: 3 | AH2: 1.6-1.8 | AI2: 3 | AK2: 0-10% | AL2: 3 | AN2: 0.9-1.7 | AO2: 3 | AQ2: 20-25% | AR2: 3 | AT2: 45-60 days | AU2: 3 | AW2: 60-90 days | AX2: 3 | AZ2: 93-94% | BA2: 3
A3: 40-60 | B3: 2 | D3: 80-90 | E3: 2 | G3: 30-40 | H3: 2 | J3: 7 | K3: 2 | M3: 30-50% | N3: 2 | P3: 20-35% | Q3: 2 | S3: 4-6% | T3: 2 | V3: 15-20% | W3: 2 | Y3: 30-35% | Z3: 2 | AB3: 110-120% | AC3: 2 | AE3: 15-20% | AF3: 2 | AH3: 1.4 - 1.6 | AI3: 2 | AK3: 10-15% | AL3: 2 | AN3: 1.7-3.3 | AO3: 2 | AQ3: 25-30% | AR3: 2 | AT3: 60-90 days | AU3: 2 | AW3: 90-180 days | AX3: 2 | AZ3: 90-92% | BA3: 2
A4: 60-80 | B4: 1 | D4: 70-80 | E4: 1 | G4: 40-50 | H4: 1 | J4: 8 | K4: 1 | M4: 50-70% | N4: 1 | P4: 5-20% | Q4: 1 | S4: 0-4% | T4: 1 | V4: 20-25% | W4: 1 | Y4: 35-40% | Z4: 1 | AB4: 100-110% | AC4: 1 | AE4: 10-15% | AF4: 1 | AH4: 1.2-1.4 | AI4: 1 | AK4: 15-20% | AL4: 1 | AN4: 3.3-6.3 | AO4: 1 | AQ4: 30-35% | AR4: 1 | AT4: 90-120 days | AU4: 1 | AW4: 180-365 days | AX4: 1 | AZ4: 85-89% | BA4: 1
A5: 80-100 | B5: 0 | D5: <70 | E5: 0 | G5: >50 | H5: 0 | J5: >8 | K5: 0 | M5: >70% | N5: 0 | P5: <5% | Q5: 0 | S5: 0 | T5: 0 | V5: >25% | W5: 0 | Y5: >40% | Z5: 0 | AB5: <100% | AC5: 0 | AE5: Less than 10% | AF5: 0 | AH5: <1.2 | AI5: 0 | AK5: >20% | AL5: 0 | AN5: >6.3 | AO5: 0 | AQ5: >35% | AR5: 0 | AT5: >120 days | AU5: 0 | AW5: >365 days | AX5: 0 | AZ5: <85% | BA5: 0
A7: Poverty Rate | D7: Santiation & Water Coverage | G7: Non Revenue Water | J7: Staff / 1000 Connection | M7: Revenue Diversification | P7: Average Tariff Differential | S7: Maintenance Costs / OPEX | V7: Electricity Costs / OPEX | Y7: Employee Costs | AB7: O&M Coverage | AE7: EBITDA / Revenue | AH7: Debt Service Coverage Ratio | AK7: Grant Dependency | AN7: Debt/Cash Available for Debt Service | AQ7: Debt to Equity | AT7: Debtor Days | AW7: Bad Debt Provision | AZ7: Billing & Collection Efficiency
AE8: Cash Reserves
AE9: Liquidity Ratio
AE10: Reduction in Debtor Days

Sheet Weight ranking
A1: Question | B1: Weight
A2: Debt/Cash Available for Debt Service | B2: 10
A3: Average Tariff Differential | B3: 8
A4: Revenue Diversification | B4: 6
A5: Non-Revenue Water | B5: 5
A6: EBITDA / Revenue | B6: 5
A7: Cash Reserves | B7: 5
A8: Debt Service Coverage Ratio | B8: 5
A9: Debt to Equity | B9: 5
A10: Debtor Days | B10: 5
A11: Reduction in Debtor Days | B11: 5
A12: Bad Debt Provision | B12: 5
A13: Billing Efficiency | B13: 5
... A24: Water Coverage | B24: 1
